{
    "1001": {
        "machineCount": 4,
        "id": "1001",
        "province": "广东",
        "arcadeName": "环游嘉年华天河店",
        "mall": "天河城",
        "address": "广东省广州市天河区天河路208号天河城6楼"
    },
    "1002": {
        "machineCount": 2,
        "id": "1002",
        "province": "广东",
        "arcadeName": "环游嘉年华番禺易发店",
        "mall": "环游嘉年华番禺易发店",
        "address": "广东省广州市番禺区市桥街易发商业街新大新百货5楼"
    },
    "1005": {
        "machineCount": 2,
        "id": "1005",
        "province": "陕西",
        "arcadeName": "哆啦乐图西安钟楼店",
        "mall": "哆啦星球",
        "address": "陕西省西安市碑林区骡马市60号文商大厦一层"
    },
    "1006": {
        "machineCount": 2,
        "id": "1006",
        "province": "上海",
        "arcadeName": "风云再起上海店",
        "mall": "风云再起上海店",
        "address": "上海市黄浦区人民大道221号迪美广场负一楼227-229#"
    },
    "1008": {
        "machineCount": 2,
        "id": "1008",
        "province": "广东",
        "arcadeName": "城市英雄东莞长安店",
        "mall": "城市英雄东莞长安店",
        "address": "广东省东莞市长安镇长青南路1号7栋万科广场三楼3039室城市英雄"
    },
    "1010": {
        "machineCount": 2,
        "id": "1010",
        "province": "湖南",
        "arcadeName": "城市英雄衡阳解放路店",
        "mall": "城市英雄衡阳解放路店",
        "address": "湖南省衡阳市石鼓区解放路26号"
    },
    "1071": {
        "machineCount": 2,
        "id": "1071",
        "province": "广东",
        "arcadeName": "环游嘉年华江门店",
        "mall": "环游嘉年华江门店",
        "address": "广东省江门市蓬江区白石大道166号汇悦城3楼"
    },
    "1073": {
        "machineCount": 4,
        "id": "1073",
        "province": "广东",
        "arcadeName": "环游嘉年华东莞民盈国贸店",
        "mall": "环游嘉年华东莞民盈国贸店",
        "address": "广东省东莞市东城街道东泰社区鸿福东路1号民盈国贸城5号楼L3001-3003"
    },
    "1077": {
        "machineCount": 2,
        "id": "1077",
        "province": "湖南",
        "arcadeName": "城市英雄长沙梅溪湖步步高店",
        "mall": "城市英雄长沙梅溪湖步步高店",
        "address": "湖南省长沙市岳麓区梅溪湖步步高负一层城市英雄"
    },
    "1080": {
        "machineCount": 2,
        "id": "1080",
        "province": "江苏",
        "arcadeName": "风云再起正洪大厦店",
        "mall": "风云再起正洪大夏店",
        "address": "江苏省南京市秦淮区洪武路38号正洪大厦102栋"
    },
    "1086": {
        "machineCount": 2,
        "id": "1086",
        "province": "陕西",
        "arcadeName": "哆啦星球小寨店",
        "mall": "哆啦星球小寨店",
        "address": "陕西省西安市雁塔区长安中路215号西旅国际一楼"
    },
    "1088": {
        "machineCount": 2,
        "id": "1088",
        "province": "湖南",
        "arcadeName": "城市英雄长沙五一广场店",
        "mall": "城市英雄长沙五一广场店",
        "address": "湖南省长沙市天心区春天百货负一楼城市英雄电玩"
    },
    "1098": {
        "machineCount": 4,
        "id": "1098",
        "province": "上海",
        "arcadeName": "上海JOYPOLIS世嘉都市乐园",
        "mall": "上海JOYPOLIS世嘉都市乐园",
        "address": "上海市普陀区中山北路3300号月星环球港四楼世嘉都市乐园"
    },
    "1135": {
        "machineCount": 2,
        "id": "1135",
        "province": "云南",
        "arcadeName": "风云再起昆明金鹰店",
        "mall": "风云再起昆明金鹰店",
        "address": "云南省昆明市威远街168号金鹰B座7楼风云再起"
    },
    "1146": {
        "machineCount": 2,
        "id": "1146",
        "province": "湖南",
        "arcadeName": "城市英雄司门口店",
        "mall": "城市英雄司门口店",
        "address": "湖南省长沙市解放西路147号"
    },
    "1182": {
        "machineCount": 2,
        "id": "1182",
        "province": "江西",
        "arcadeName": "城市英雄赣州店",
        "mall": "城市英雄赣州店",
        "address": "江西省赣州市章贡区红旗大道33号步步高新天地四楼"
    },
    "1186": {
        "machineCount": 2,
        "id": "1186",
        "province": "湖南",
        "arcadeName": "壹零壹潮漫万家丽负一楼店（偶予电玩）",
        "mall": "长沙市芙蓉区偶予电子游艺厅",
        "address": "湖南省长沙市芙蓉区东沌渡街道万家丽中路一段99－101号B1楼B42&B43－1号商铺"
    },
    "1187": {
        "machineCount": 4,
        "id": "1187",
        "province": "上海",
        "arcadeName": "上海烈火游戏机娱乐有限公司",
        "mall": "上海烈火游戏机娱乐有限公司",
        "address": "上海市静安区江宁路77号4楼"
    },
    "1192": {
        "machineCount": 2,
        "id": "1192",
        "province": "天津",
        "arcadeName": "51区动漫游乐天津西青店",
        "mall": "51区动漫游乐天津西青店",
        "address": "天津市西青区中北镇阜盛道永旺梦乐城2楼51区动漫游乐场"
    },
    "1205": {
        "machineCount": 2,
        "id": "1205",
        "province": "山西",
        "arcadeName": "阿凡达电玩山西太原柳巷店",
        "mall": "阿凡达电玩山西太原柳巷店",
        "address": "山西省太原市迎泽区柳巷商业街工贸大厦四楼阿凡达电玩嘉年华"
    },
    "1208": {
        "machineCount": 2,
        "id": "1208",
        "province": "江西",
        "arcadeName": "城市英雄江西南昌店",
        "mall": "城市英雄江西南昌店",
        "address": "江西省南昌市新建区长棱大道新城吾悦广场2楼"
    },
    "1217": {
        "machineCount": 2,
        "id": "1217",
        "province": "广东",
        "arcadeName": "环游嘉年华广州黄埔绿地店",
        "mall": "环游嘉年华广州黄埔绿地店",
        "address": "广东省广州市黄埔区亿创大街3号绿地缤纷城3楼301铺"
    },
    "1243": {
        "machineCount": 2,
        "id": "1243",
        "province": "福建",
        "arcadeName": "乐炫风福州鼓楼东百中心店",
        "mall": "乐炫风福州鼓楼东百中心店",
        "address": "福建省福州市鼓楼区东街东百中心C馆负一楼乐炫风"
    },
    "1286": {
        "machineCount": 2,
        "id": "1286",
        "province": "广东",
        "arcadeName": "反斗乐园深圳宝安壹方城星际传奇店",
        "mall": "反斗乐园深圳宝安壹方城星际传奇店",
        "address": "广东省深圳市宝安区宝安中心壹方城购物中心三楼星际传奇"
    },
    "1300": {
        "machineCount": 2,
        "id": "1300",
        "province": "广东",
        "arcadeName": "极客森超乐场深圳宝能城店",
        "mall": "极客森超乐场深圳宝能城店",
        "address": "广东省深圳市南山区西丽留仙大道塘朗地铁站C出口宝能城三楼极客森超乐场"
    },
    "1312": {
        "machineCount": 1,
        "id": "1312",
        "province": "吉林",
        "arcadeName": "城市英雄电玩长春欧亚新生活店",
        "mall": "城市英雄电玩长春欧亚新生活店",
        "address": "吉林省长春市朝阳区红旗街新民广场欧亚新生活5楼城市英雄电玩城"
    },
    "1328": {
        "machineCount": 1,
        "id": "1328",
        "province": "内蒙古",
        "arcadeName": "酷乐大玩家鄂尔多斯店",
        "mall": "酷乐大玩家鄂尔多斯店",
        "address": "内蒙古鄂尔多斯市东胜区星河COCO City二期二楼"
    },
    "1352": {
        "machineCount": 2,
        "id": "1352",
        "province": "江苏",
        "arcadeName": "星悦潮玩无锡店",
        "mall": "星悦潮玩无锡店",
        "address": "江苏省无锡市锡山区锡东八佰伴3楼星悦潮玩"
    },
    "1391": {
        "machineCount": 1,
        "id": "1391",
        "province": "吉林",
        "arcadeName": "城市英雄长春亚泰新动力店",
        "mall": "城市英雄长春亚太新动力店",
        "address": "吉林省长春市二道区东盛大街与吉林大路交汇亚泰新动力"
    },
    "1397": {
        "machineCount": 2,
        "id": "1397",
        "province": "江苏",
        "arcadeName": "风云再起无锡清扬茂业天地店",
        "mall": "风云再起无锡清扬茂业天地店",
        "address": "江苏省无锡市梁溪区清扬路128号茂业天地3楼风云再起"
    },
    "1417": {
        "machineCount": 2,
        "id": "1417",
        "province": "广东",
        "arcadeName": "哇哇哇游乐城广州天河正佳店",
        "mall": "哇哇哇游乐城广州天河正佳店",
        "address": "广东省广州市天河区天河路228号正佳广场七楼"
    },
    "1447": {
        "machineCount": 2,
        "id": "1447",
        "province": "天津",
        "arcadeName": "PPG潮玩汇天津大悦城店",
        "mall": "PPG潮玩汇",
        "address": "天津市南开区南门外大街大悦城南区四楼"
    },
    "1452": {
        "machineCount": 2,
        "id": "1452",
        "province": "广东",
        "arcadeName": "极客森深圳万科里店",
        "mall": "极客森深圳万科里店",
        "address": "广东省深圳市龙岗区龙城万科里负一楼极客森"
    },
    "1522": {
        "machineCount": 4,
        "id": "1522",
        "province": "湖南",
        "arcadeName": "子洋联盟长沙望城奥莱店",
        "mall": "子洋联盟长沙望城奥莱店",
        "address": "湖南省长沙市望城区金星北路砂之船奥莱3楼子洋联盟动漫体验中心"
    },
    "1620": {
        "machineCount": 2,
        "id": "1620",
        "province": "陕西",
        "arcadeName": "城市英雄西安熙地港店",
        "mall": "城市英雄西安熙地港店",
        "address": "陕西省西安市未央区凤城七路熙地港购物中心五楼"
    },
    "1623": {
        "machineCount": 2,
        "id": "1623",
        "province": "上海",
        "arcadeName": "星河部落川沙百联店",
        "mall": "星河部落川沙百联店",
        "address": "上海市浦东新区5398号3楼"
    },
    "1627": {
        "machineCount": 4,
        "id": "1627",
        "province": "广东",
        "arcadeName": "环游嘉年华东莞运动汇一城店",
        "mall": "环游嘉年华东莞运动汇一城店",
        "address": "广东省东莞市南城街道鸿福路200号第一财富中心5栋103-202室"
    },
    "1661": {
        "machineCount": 2,
        "id": "1661",
        "province": "广东",
        "arcadeName": "朗玩深圳壹方天地店",
        "mall": "朗玩深圳壹方天地店",
        "address": "广东省深圳市龙华区龙华街道景龙社区壹成中心花园三区E座壹方天地C区L1-001A~L4-001"
    },
    "1668": {
        "machineCount": 2,
        "id": "1668",
        "province": "辽宁",
        "arcadeName": "万有引力沈阳欧亚长青城店",
        "mall": "万有引力沈阳欧亚长青城店",
        "address": "辽宁省沈阳市浑南区长青南街6甲号欧亚长青城"
    },
    "1702": {
        "machineCount": 2,
        "id": "1702",
        "province": "上海",
        "arcadeName": "朗玩上海宝山日月光店",
        "mall": "朗玩上海宝山日月光店",
        "address": "上海市宝山区沪太路1933号日月光中心三楼朗玩娱乐中心"
    },
    "1719": {
        "machineCount": 2,
        "id": "1719",
        "province": "四川",
        "arcadeName": "环游嘉年华成都武侯店",
        "mall": "环游嘉年华成都武侯店",
        "address": "四川省成都市武侯区仁和新城购物中心5楼"
    },
    "1721": {
        "machineCount": 2,
        "id": "1721",
        "province": "浙江",
        "arcadeName": "星河部落海宁长安奥特莱斯店",
        "mall": "星河部落海宁长安奥特莱斯店",
        "address": "浙江省海宁市长安镇启潮路199号奥特莱斯二期1号楼3楼E301-E314星河部落电玩城"
    },
    "1750": {
        "machineCount": 2,
        "id": "1750",
        "province": "山东",
        "arcadeName": "51区超级乐园济南印象城店",
        "mall": "51区超级乐园济南印象城店",
        "address": "山东省济南市历城区花园路136号印象城5楼L519-L522"
    },
    "1753": {
        "machineCount": 2,
        "id": "1753",
        "province": "山东",
        "arcadeName": "51区青岛市北悦荟广场店",
        "mall": "51区青岛市北悦荟广场店",
        "address": "山东省青岛市市北区人民路269号悦荟广场5楼"
    },
    "1760": {
        "machineCount": 2,
        "id": "1760",
        "province": "湖南",
        "arcadeName": "城市英雄岳阳步行街店",
        "mall": "城市英雄岳阳步行街店",
        "address": "湖南省岳阳市岳阳楼区步行街康星百货负一楼"
    },
    "1778": {
        "machineCount": 2,
        "id": "1778",
        "province": "重庆",
        "arcadeName": "城市英雄重庆龙湖时代天街店",
        "mall": "城市英雄重庆喜盈门范城店",
        "address": "重庆市渝中区大坪龙湖时代天街A馆UG层"
    },
    "1811": {
        "machineCount": 2,
        "id": "1811",
        "province": "吉林",
        "arcadeName": "炫动四方长春居然世界里店",
        "mall": "炫动四方长春店",
        "address": "吉林省长春市高新区居然世界里三楼炫动四方电玩城"
    },
    "1858": {
        "machineCount": 2,
        "id": "1858",
        "province": "江苏",
        "arcadeName": "风云再起徐州鼓楼苏宁广场店",
        "mall": "风云再起徐州鼓楼苏宁广场店",
        "address": "江苏省徐州市鼓楼区淮海东路29号苏宁广场3F326"
    },
    "1869": {
        "machineCount": 2,
        "id": "1869",
        "province": "浙江",
        "arcadeName": "米吉姆宁波鄞州银泰店",
        "mall": "米吉姆宁波鄞州银泰店",
        "address": "浙江省宁波市鄞州区首南街道天童南路1088号句章东路999号银泰环球城内购物中心3F层"
    },
    "1896": {
        "machineCount": 2,
        "id": "1896",
        "province": "广东",
        "arcadeName": "环游嘉年华珠海华发店",
        "mall": "环游嘉年华珠海华发店",
        "address": "广东省珠海市香洲区珠海大道8号华发商都C馆三楼C3031号环游嘉年华"
    },
    "1917": {
        "machineCount": 2,
        "id": "1917",
        "province": "江苏",
        "arcadeName": "朗玩南京江宁金鹰店",
        "mall": "朗玩南京江宁金鹰店",
        "address": "江苏省南京市江宁区双龙大道1688号金鹰购物中心1F-3F"
    },
    "1933": {
        "machineCount": 2,
        "id": "1933",
        "province": "广东",
        "arcadeName": "天空之城东莞店",
        "mall": "天空之城东莞店",
        "address": "广东省东莞市东城东路229号星河城3F-302号商铺"
    },
    "1975": {
        "machineCount": 2,
        "id": "1975",
        "province": "天津",
        "arcadeName": "51区超级乐园天津和平店",
        "mall": "51区超级乐园天津和平店",
        "address": "天津市和平区滨江道商业街143号"
    },
    "1983": {
        "machineCount": 2,
        "id": "1983",
        "province": "北京",
        "arcadeName": "风云再起北京西西友谊店",
        "mall": "风云再起北京西西友谊店",
        "address": "北京市西城区金融街西西友谊商城二层风云再起"
    },
    "2005": {
        "machineCount": 2,
        "id": "2005",
        "province": "重庆",
        "arcadeName": "城市英雄重庆大学城店",
        "mall": "城市英雄重庆大学城店",
        "address": "重庆沙坪坝区熙街商业街C区1C-20城市英雄电玩城"
    },
    "2029": {
        "machineCount": 2,
        "id": "2029",
        "province": "江苏",
        "arcadeName": "天空之城南京浦口龙湖天街店",
        "mall": "天空之城南京浦口龙湖天街店",
        "address": "江苏省南京市浦口区文景路99号龙湖天街3楼天空之城"
    },
    "2034": {
        "machineCount": 2,
        "id": "2034",
        "province": "山西",
        "arcadeName": "PPG潮玩汇大同平城店",
        "mall": "PPG潮玩汇大同店",
        "address": "山西省大同市平城区绿地缤纷汇6号楼二层"
    },
    "2037": {
        "machineCount": 2,
        "id": "2037",
        "province": "广东",
        "arcadeName": "米其动漫东莞虎门店",
        "mall": "米其动漫东莞虎门店",
        "address": "广东省东莞市虎门镇连升中路44号地标广场（天虹商场）2号楼1层"
    },
    "2040": {
        "machineCount": 2,
        "id": "2040",
        "province": "福建",
        "arcadeName": "第一回合厦门湖里海上世界店",
        "mall": "第一回合厦门湖里海上世界店",
        "address": "福建省厦门市湖里区双狮西路海上世界购物中心2F-L222第一回合"
    },
    "2045": {
        "machineCount": 2,
        "id": "2045",
        "province": "湖南",
        "arcadeName": "反斗乐园派长沙雨花星城店",
        "mall": "反斗乐园长沙雨花星城店",
        "address": "湖南省长沙市雨花区中意一路与湘府路交叉口步步高星城天地L3-3046"
    },
    "2046": {
        "machineCount": 2,
        "id": "2046",
        "province": "山东",
        "arcadeName": "super101青岛崂山店",
        "mall": "super101青岛崂山店",
        "address": "山东省青岛市崂山区丽达广场super101"
    },
    "2051": {
        "machineCount": 2,
        "id": "2051",
        "province": "北京",
        "arcadeName": "可多梦北京丰台店",
        "mall": "可多梦北京丰台店",
        "address": "北京市丰台区南四环西路76号花乡奥莱村13号楼13101-B号"
    },
    "2064": {
        "machineCount": 2,
        "id": "2064",
        "province": "河南",
        "arcadeName": "幻游嘉年华郑州二七店",
        "mall": "幻游嘉年华郑州二七店",
        "address": "河南省郑州市二七区德化街100号百年德化风情购物公园负一层F100号郑州幻游嘉年华游乐体验中心"
    },
    "2067": {
        "machineCount": 2,
        "id": "2067",
        "province": "重庆",
        "arcadeName": "童年搭档重庆江北店",
        "mall": "童年搭档重庆江北店",
        "address": "重庆市江北区观音桥天天尚街童年搭档"
    },
    "2069": {
        "machineCount": 2,
        "id": "2069",
        "province": "北京",
        "arcadeName": "魔方MIX北京亦庄华联店",
        "mall": "魔方MIX家庭娱乐中心北京亦庄店",
        "address": "北京市亦庄开发区荣华中路力宝华联购物中心3楼魔方MIX家庭娱乐中心"
    },
    "2070": {
        "machineCount": 2,
        "id": "2070",
        "province": "浙江",
        "arcadeName": "第一回合杭州湖滨银泰店",
        "mall": "第一回合杭州湖滨银泰店",
        "address": "浙江省杭州市上城区延安路258号湖滨银泰C1区负一楼第一回合"
    },
    "2072": {
        "machineCount": 2,
        "id": "2072",
        "province": "北京",
        "arcadeName": "魔方MIX北京顺义华联店",
        "mall": "魔方MIX北京顺义华联店",
        "address": "北京市顺义区新顺南大街8号华联购物中心3楼魔方MIX家庭娱乐中心"
    },
    "2079": {
        "machineCount": 2,
        "id": "2079",
        "province": "四川",
        "arcadeName": "泛时空成都武侯店",
        "mall": "泛时空成都武侯店",
        "address": "四川省成都市武侯区天府大道北段1777号招商大魔方三楼3028泛时空"
    },
    "2087": {
        "machineCount": 2,
        "id": "2087",
        "province": "湖北",
        "arcadeName": "真快活武汉梦时代店",
        "mall": "真快活武汉梦时代店",
        "address": "湖北省武汉市武昌区武珞路628号武商梦时代B座801真快活电玩"
    },
    "2097": {
        "machineCount": 2,
        "id": "2097",
        "province": "浙江",
        "arcadeName": "泛时空电玩绍兴越城店",
        "mall": "泛时空电玩绍兴越城店",
        "address": "浙江省绍兴市越城区府山街道国金大悦城L3-15.16泛时空电玩城"
    },
    "2101": {
        "machineCount": 2,
        "id": "2101",
        "province": "江苏",
        "arcadeName": "天空之城建邺吾悦广场店",
        "mall": "天空之城建邺吾悦广场店",
        "address": "江苏省南京市建邺区汉中门大街299号吾悦广场二楼天空之城"
    },
    "2107": {
        "machineCount": 4,
        "id": "2107",
        "province": "广东",
        "arcadeName": "WAGAME东莞国贸中心",
        "mall": "WAGAME东莞国贸中心",
        "address": "广东省东莞市东城街道东泰社区鸿福东路1号民盈国贸城3L中庭"
    },
    "2108": {
        "machineCount": 2,
        "id": "2108",
        "province": "山东",
        "arcadeName": "51区青岛李沧万达店",
        "mall": "51区青岛李沧万达店",
        "address": "山东省青岛市李沧区巨峰路万达广场2楼51区超级乐园"
    },
    "2112": {
        "machineCount": 2,
        "id": "2112",
        "province": "广东",
        "arcadeName": "风云再起广州海珠富力店",
        "mall": "风云再起广州海珠富力店",
        "address": "广东省广州市海珠区富力海珠城B区6楼风云再起"
    },
    "2122": {
        "machineCount": 3,
        "id": "2122",
        "province": "广东",
        "arcadeName": "就好潮玩馆深圳宝安店",
        "mall": "就好潮玩馆深圳宝安店",
        "address": "广东省深圳市宝安区海城路1号前城滨海花园1栋B座负一层B146-151号"
    }
}